FolderArchaeologist/__init__.py
FolderArchaeologist/categories.py
FolderArchaeologist/features.py
FolderArchaeologist/main.py
FolderArchaeologist/utilities.py
folderarchaeologist-1.0.1.dist-info/licenses/LICENSE
folderarchaeologist-1.0.1.dist-info/METADATA
folderarchaeologist-1.0.1.dist-info/WHEEL
folderarchaeologist-1.0.1.dist-info/entry_points.txt
folderarchaeologist-1.0.1.dist-info/top_level.txt
folderarchaeologist-1.0.1.dist-info/RECORD
