Metadata-Version: 2.4
Name: FolderArchaeologist
Version: 1.0.1
Summary: A python based CLI file management tool that gamifies managing files in a cluttered folder.
Author: Koffandaff, Bond0707
License: MIT
Project-URL: Homepage, https://github.com/bond0707/Folder-Archaeologist
Project-URL: Bug Tracker, https://github.com/bond0707/Folder-Archaeologist/issues
Classifier: Programming Language :: Python :: 3
Classifier: Operating System :: OS Independent
Classifier: Topic :: Terminals
Classifier: Environment :: Console
Requires-Python: >=3.8
License-File: LICENSE
Requires-Dist: rich
Requires-Dist: send2trash
Dynamic: license-file
